tqml/__init__.py
tqml/__init__.pyi
tqml/copilot/__init__.py
tqml/copilot/__init__.pyi
tqml/copilot/chat.py
tqml/copilot/chat.pyi
tqml/pyarmor_runtime_005970/__init__.py
tqml/pyarmor_runtime_005970/py310/darwin_aarch64/pyarmor_runtime.so
tqml/pyarmor_runtime_005970/py310/darwin_x86_64/pyarmor_runtime.so
tqml/pyarmor_runtime_005970/py310/linux_x86_64/pyarmor_runtime.so
tqml/pyarmor_runtime_005970/py310/windows_x86_64/pyarmor_runtime.pyd
tqml/pyarmor_runtime_005970/py311/darwin_aarch64/pyarmor_runtime.so
tqml/pyarmor_runtime_005970/py311/darwin_x86_64/pyarmor_runtime.so
tqml/pyarmor_runtime_005970/py311/linux_x86_64/pyarmor_runtime.so
tqml/pyarmor_runtime_005970/py311/windows_x86_64/pyarmor_runtime.pyd
tqml/pyarmor_runtime_005970/py312/darwin_aarch64/pyarmor_runtime.so
tqml/pyarmor_runtime_005970/py312/darwin_x86_64/pyarmor_runtime.so
tqml/pyarmor_runtime_005970/py312/linux_x86_64/pyarmor_runtime.so
tqml/pyarmor_runtime_005970/py312/windows_x86_64/pyarmor_runtime.pyd
tqml/pyarmor_runtime_005970/py39/darwin_aarch64/pyarmor_runtime.so
tqml/pyarmor_runtime_005970/py39/darwin_x86_64/pyarmor_runtime.so
tqml/pyarmor_runtime_005970/py39/linux_x86_64/pyarmor_runtime.so
tqml/pyarmor_runtime_005970/py39/windows_x86_64/pyarmor_runtime.pyd
tqml/tqcirc/__init__.py
tqml/tqcirc/__init__.pyi
tqml/tqcirc/barren_plateaus.py
tqml/tqcirc/barren_plateaus.pyi
tqml/tqcirc/fisher.py
tqml/tqcirc/fisher.pyi
tqml/tqcirc/fourier.py
tqml/tqcirc/fourier.pyi
tqml/tqcirc/legacy_fisher.py
tqml/tqcirc/legacy_fisher.pyi
tqml/tqcirc/zx_calculus.py
tqml/tqcirc/zx_calculus.pyi
tqml/tqnet/LDE.py
tqml/tqnet/LDE.pyi
tqml/tqnet/__init__.py
tqml/tqnet/__init__.pyi
tqml/tqnet/_base.py
tqml/tqnet/_base.pyi
tqml/tqnet/exceptions.py
tqml/tqnet/exceptions.pyi
tqml/tqnet/layers/__init__.py
tqml/tqnet/layers/__init__.pyi
tqml/tqnet/layers/_reuploading/both.py
tqml/tqnet/layers/_reuploading/both.pyi
tqml/tqnet/layers/_reuploading/both_both.py
tqml/tqnet/layers/_reuploading/both_both.pyi
tqml-5.13.2.dist-info/METADATA
tqml-5.13.2.dist-info/WHEEL
tqml-5.13.2.dist-info/licenses/LICENSE.md
tqml-5.13.2.dist-info/licenses/NOTICE.md
tqml-5.13.2.dist-info/RECORD
