Metadata-Version: 2.4
Name: tqml
Version: 5.13.2
Summary: Quantum Machine Learning Library
License: # TQML License
License-File: LICENSE.md
License-File: NOTICE.md
Author: Terra Quantum
Requires-Python: >=3.9,<4.0
Classifier: License :: Other/Proprietary License
Classifier: Programming Language :: Python :: 3
Classifier: Programming Language :: Python :: 3.9
Classifier: Programming Language :: Python :: 3.10
Classifier: Programming Language :: Python :: 3.11
Classifier: Programming Language :: Python :: 3.12
Classifier: Programming Language :: Python :: 3.13
Classifier: Programming Language :: Python :: 3.14
Requires-Dist: autoray (>=0.7,<0.8)
Requires-Dist: keygen-py (>=0.1.8,<0.2.0)
Requires-Dist: matplotlib (>=3.8,<3.9)
Requires-Dist: mycolorpy (>=1.5.1,<2.0.0)
Requires-Dist: optuna (>=2.10.0,<3.0.0)
Requires-Dist: pennylane (>=0.38,<0.39)
Requires-Dist: pennylane-lightning (>=0.38,<0.39)
Requires-Dist: py-machineid (>=0.7.0,<0.8.0)
Requires-Dist: pyzx (>=0.8.0,<0.9.0)
Requires-Dist: ray[train,tune] (>=2.10.0,<3.0.0)
Requires-Dist: scikit-learn (>=1.4.1,<2.0.0)
Requires-Dist: torch (>=2.7,<2.8)
